{
  "displayFieldName" : "ME_NAME", 
  "fieldAliases" : {
    "ME_NAME" : "ME_NAME", 
    "OBJECTID" : "OBJECTID", 
    "SHP_FILE_ID" : "SHP_FILE_ID", 
    "ME_ID" : "ME_ID", 
    "LOCAL_WELL_NBR" : "LOCAL_WELL_NBR", 
    "SWN" : "SWN", 
    "CASGEM_WELL_ID" : "CASGEM_WELL_ID", 
    "GW_BASIN_NAME" : "GW_BASIN_NAME", 
    "GW_BASIN_CODE" : "GW_BASIN_CODE", 
    "WELL_USE" : "WELL_USE", 
    "TOTAL_WELL_DEPTH" : "TOTAL_WELL_DEPTH", 
    "HAS_WELL_CONST_DATA" : "HAS_WELL_CONST_DATA", 
    "COUNTY" : "COUNTY", 
    "COOP_AGENCY" : "COOP_AGENCY", 
    "STATUS" : "STATUS", 
    "SUBMIT_DATE" : "SUBMIT_DATE", 
    "COMPLETION_RPT_NBR" : "COMPLETION_RPT_NBR", 
    "CASGEM_STATION_ID" : "CASGEM_STATION_ID", 
    "HYDROLOGIC_REGION" : "HYDROLOGIC_REGION", 
    "DWR_REGION_OFFICE" : "DWR_REGION_OFFICE", 
    "LATITUDE" : "LATITUDE", 
    "LONGITUDE" : "LONGITUDE", 
    "IS_VOLUNTARY" : "IS_VOLUNTARY"
  }, 
  "geometryType" : "esriGeometryPoint", 
  "spatialReference" : {
    "wkid" : 4326
  }, 
  "features" : [
    {
      "attributes" : {
        "ME_NAME" : "Department of Water Resources", 
        "OBJECTID" : 202, 
        "SHP_FILE_ID" : null, 
        "ME_ID" : "1", 
        "LOCAL_WELL_NBR" : null, 
        "SWN" : "03S16E03C001M", 
        "CASGEM_WELL_ID" : "2136", 
        "GW_BASIN_NAME" : " ", 
        "GW_BASIN_CODE" : " ", 
        "WELL_USE" : "Unknown", 
        "TOTAL_WELL_DEPTH" : "Unknown", 
        "HAS_WELL_CONST_DATA" : "N", 
        "COUNTY" : "Mariposa", 
        "COOP_AGENCY" : " ", 
        "STATUS" : "Y", 
        "SUBMIT_DATE" : "06/01/2011", 
        "COMPLETION_RPT_NBR" : "Not Available", 
        "CASGEM_STATION_ID" : "377118N1201988W001", 
        "HYDROLOGIC_REGION" : " ", 
        "DWR_REGION_OFFICE" : null, 
        "LATITUDE" : "37.7118", 
        "LONGITUDE" : "-120.1988", 
        "IS_VOLUNTARY" : "Y"
      }, 
      "geometry" : 
      {
        "x" : -120.1988, 
        "y" : 37.7118
      }
    }, 
    {
      "attributes" : {
        "ME_NAME" : "Department of Water Resources", 
        "OBJECTID" : 1193, 
        "SHP_FILE_ID" : null, 
        "ME_ID" : "1", 
        "LOCAL_WELL_NBR" : null, 
        "SWN" : "02S17E19J001M", 
        "CASGEM_WELL_ID" : "3233", 
        "GW_BASIN_NAME" : " ", 
        "GW_BASIN_CODE" : " ", 
        "WELL_USE" : "Unknown", 
        "TOTAL_WELL_DEPTH" : "Unknown", 
        "HAS_WELL_CONST_DATA" : "N", 
        "COUNTY" : "Mariposa", 
        "COOP_AGENCY" : " ", 
        "STATUS" : "Y", 
        "SUBMIT_DATE" : "06/01/2011", 
        "COMPLETION_RPT_NBR" : "Not Available", 
        "CASGEM_STATION_ID" : "377466N1201318W001", 
        "HYDROLOGIC_REGION" : " ", 
        "DWR_REGION_OFFICE" : null, 
        "LATITUDE" : "37.7466", 
        "LONGITUDE" : "-120.1318", 
        "IS_VOLUNTARY" : "Y"
      }, 
      "geometry" : 
      {
        "x" : -120.1318, 
        "y" : 37.7466000000001
      }
    }, 
    {
      "attributes" : {
        "ME_NAME" : "Department of Water Resources", 
        "OBJECTID" : 5307, 
        "SHP_FILE_ID" : null, 
        "ME_ID" : "1", 
        "LOCAL_WELL_NBR" : null, 
        "SWN" : "05S18E07K001M", 
        "CASGEM_WELL_ID" : "7662", 
        "GW_BASIN_NAME" : " ", 
        "GW_BASIN_CODE" : " ", 
        "WELL_USE" : "Unknown", 
        "TOTAL_WELL_DEPTH" : "Unknown", 
        "HAS_WELL_CONST_DATA" : "N", 
        "COUNTY" : "Mariposa", 
        "COOP_AGENCY" : " ", 
        "STATUS" : "Y", 
        "SUBMIT_DATE" : "06/01/2011", 
        "COMPLETION_RPT_NBR" : "Not Available", 
        "CASGEM_STATION_ID" : "375107N1200393W001", 
        "HYDROLOGIC_REGION" : " ", 
        "DWR_REGION_OFFICE" : null, 
        "LATITUDE" : "37.5107", 
        "LONGITUDE" : "-120.0393", 
        "IS_VOLUNTARY" : "Y"
      }, 
      "geometry" : 
      {
        "x" : -120.0393, 
        "y" : 37.5107
      }
    }, 
    {
      "attributes" : {
        "ME_NAME" : "Department of Water Resources", 
        "OBJECTID" : 5308, 
        "SHP_FILE_ID" : null, 
        "ME_ID" : "1", 
        "LOCAL_WELL_NBR" : null, 
        "SWN" : "05S18E18C001M", 
        "CASGEM_WELL_ID" : "7663", 
        "GW_BASIN_NAME" : " ", 
        "GW_BASIN_CODE" : " ", 
        "WELL_USE" : "Unknown", 
        "TOTAL_WELL_DEPTH" : "Unknown", 
        "HAS_WELL_CONST_DATA" : "N", 
        "COUNTY" : "Mariposa", 
        "COOP_AGENCY" : " ", 
        "STATUS" : "Y", 
        "SUBMIT_DATE" : "06/01/2011", 
        "COMPLETION_RPT_NBR" : "Not Available", 
        "CASGEM_STATION_ID" : "375049N1200418W001", 
        "HYDROLOGIC_REGION" : " ", 
        "DWR_REGION_OFFICE" : null, 
        "LATITUDE" : "37.5049", 
        "LONGITUDE" : "-120.0418", 
        "IS_VOLUNTARY" : "Y"
      }, 
      "geometry" : 
      {
        "x" : -120.0418, 
        "y" : 37.5049000000001
      }
    }, 
    {
      "attributes" : {
        "ME_NAME" : "Department of Water Resources", 
        "OBJECTID" : 5309, 
        "SHP_FILE_ID" : null, 
        "ME_ID" : "1", 
        "LOCAL_WELL_NBR" : null, 
        "SWN" : "05S18E36Q001M", 
        "CASGEM_WELL_ID" : "7664", 
        "GW_BASIN_NAME" : " ", 
        "GW_BASIN_CODE" : " ", 
        "WELL_USE" : "Unknown", 
        "TOTAL_WELL_DEPTH" : "Unknown", 
        "HAS_WELL_CONST_DATA" : "N", 
        "COUNTY" : "Mariposa", 
        "COOP_AGENCY" : " ", 
        "STATUS" : "Y", 
        "SUBMIT_DATE" : "06/01/2011", 
        "COMPLETION_RPT_NBR" : "Not Available", 
        "CASGEM_STATION_ID" : "374471N1199471W001", 
        "HYDROLOGIC_REGION" : " ", 
        "DWR_REGION_OFFICE" : null, 
        "LATITUDE" : "37.4471", 
        "LONGITUDE" : "-119.9471", 
        "IS_VOLUNTARY" : "Y"
      }, 
      "geometry" : 
      {
        "x" : -119.9471, 
        "y" : 37.4471
      }
    }, 
    {
      "attributes" : {
        "ME_NAME" : "Department of Water Resources", 
        "OBJECTID" : 3684, 
        "SHP_FILE_ID" : null, 
        "ME_ID" : "1", 
        "LOCAL_WELL_NBR" : null, 
        "SWN" : "06S17E03J001M", 
        "CASGEM_WELL_ID" : "5932", 
        "GW_BASIN_NAME" : " ", 
        "GW_BASIN_CODE" : " ", 
        "WELL_USE" : "Unknown", 
        "TOTAL_WELL_DEPTH" : "Unknown", 
        "HAS_WELL_CONST_DATA" : "N", 
        "COUNTY" : "Mariposa", 
        "COOP_AGENCY" : " ", 
        "STATUS" : "Y", 
        "SUBMIT_DATE" : "06/01/2011", 
        "COMPLETION_RPT_NBR" : "Not Available", 
        "CASGEM_STATION_ID" : "374399N1200871W001", 
        "HYDROLOGIC_REGION" : " ", 
        "DWR_REGION_OFFICE" : null, 
        "LATITUDE" : "37.4399", 
        "LONGITUDE" : "-120.0871", 
        "IS_VOLUNTARY" : "Y"
      }, 
      "geometry" : 
      {
        "x" : -120.0871, 
        "y" : 37.4399000000001
      }
    }, 
    {
      "attributes" : {
        "ME_NAME" : "Department of Water Resources", 
        "OBJECTID" : 24029, 
        "SHP_FILE_ID" : null, 
        "ME_ID" : "1", 
        "LOCAL_WELL_NBR" : null, 
        "SWN" : "03S16E03F001M", 
        "CASGEM_WELL_ID" : "26580", 
        "GW_BASIN_NAME" : " ", 
        "GW_BASIN_CODE" : " ", 
        "WELL_USE" : "Unknown", 
        "TOTAL_WELL_DEPTH" : "Unknown", 
        "HAS_WELL_CONST_DATA" : "N", 
        "COUNTY" : "Mariposa", 
        "COOP_AGENCY" : " ", 
        "STATUS" : "Y", 
        "SUBMIT_DATE" : "06/01/2011", 
        "COMPLETION_RPT_NBR" : "Not Available", 
        "CASGEM_STATION_ID" : "377074N1201966W001", 
        "HYDROLOGIC_REGION" : " ", 
        "DWR_REGION_OFFICE" : null, 
        "LATITUDE" : "37.7074", 
        "LONGITUDE" : "-120.1966", 
        "IS_VOLUNTARY" : "Y"
      }, 
      "geometry" : 
      {
        "x" : -120.1966, 
        "y" : 37.7074000000001
      }
    }, 
    {
      "attributes" : {
        "ME_NAME" : "Department of Water Resources", 
        "OBJECTID" : 26491, 
        "SHP_FILE_ID" : null, 
        "ME_ID" : "1", 
        "LOCAL_WELL_NBR" : null, 
        "SWN" : "05S18E07L001M", 
        "CASGEM_WELL_ID" : "29259", 
        "GW_BASIN_NAME" : " ", 
        "GW_BASIN_CODE" : " ", 
        "WELL_USE" : "Unknown", 
        "TOTAL_WELL_DEPTH" : "Unknown", 
        "HAS_WELL_CONST_DATA" : "N", 
        "COUNTY" : "Mariposa", 
        "COOP_AGENCY" : " ", 
        "STATUS" : "Y", 
        "SUBMIT_DATE" : "06/01/2011", 
        "COMPLETION_RPT_NBR" : "Not Available", 
        "CASGEM_STATION_ID" : "375118N1200418W001", 
        "HYDROLOGIC_REGION" : " ", 
        "DWR_REGION_OFFICE" : null, 
        "LATITUDE" : "37.5118", 
        "LONGITUDE" : "-120.0418", 
        "IS_VOLUNTARY" : "Y"
      }, 
      "geometry" : 
      {
        "x" : -120.0418, 
        "y" : 37.5118000000001
      }
    }
  ]
}